{
    "work_dir": "/app/work",
    "artifact_dir": "/app/artifacts",
    "aiohttp_max_connections": 10,
    "checksums_digests": ["sha512", "sha256"],
    "blobs_needing_prettynaming_contents": [
        "target.test_packages.json"
    ],
    "taskcluster_scope_prefix": "project:releng:beetmover:",
    "verbose": true,
    "zip_max_file_size_in_mb": 300,
    "bucket_config": {
        "nightly": {
            "credentials": {
                "id": {"$eval": "NIGHTLY_ID"},
                "key": {"$eval": "NIGHTLY_KEY"}
            },
            "buckets": {
              "firefox": "net-mozaws-prod-delivery-firefox",
              "fennec": "net-mozaws-prod-delivery-archive",
              "mobile": "net-mozaws-prod-delivery-archive",
              "devedition": "net-mozaws-prod-delivery-archive"
            },
            "url_prefix": "https://archive.mozilla.org"
        },
        "release": {
            "credentials": {
                "id": {"$eval": "RELEASE_ID"},
                "key": {"$eval": "RELEASE_KEY"}
            },
            "buckets": {
              "firefox": "net-mozaws-prod-delivery-firefox",
              "fennec": "net-mozaws-prod-delivery-archive",
              "mobile": "net-mozaws-prod-delivery-archive",
              "devedition": "net-mozaws-prod-delivery-archive"
            },
            "url_prefix": "https://archive.mozilla.org"
        },
        "partner": {
            "credentials": {
                "id": {"$eval": "PARTNER_ID"},
                "key": {"$eval": "PARTNER_KEY"}
            },
            "buckets": {
              "firefox": "fxpartners-distros"
            }
        },
        "maven-production": {
            "credentials": {
                "id": {"$eval": "MAVEN_PRODUCTION_ID"},
                "key": {"$eval": "MAVEN_PRODUCTION_KEY"}
            },
            "buckets": {
                "geckoview": "maven-default-s3-upload-bucket-1705kkmo2aj3c"
            }
        },
        "dep-partner": {
            "credentials": {
                "id": {"$eval": "DEP_PARTNER_ID"},
                "key": {"$eval": "DEP_PARTNER_KEY"}
            },
            "buckets": {
              "firefox": "mozilla-releng-dep-partner"
            }
        },
        "dep": {
            "credentials": {
                "id": {"$eval": "DEP_ID"},
                "key": {"$eval": "DEP_KEY"}
            },
            "buckets": {
              "firefox": "net-mozaws-stage-delivery-firefox",
              "fennec": "net-mozaws-stage-delivery-archive",
              "mobile": "net-mozaws-stage-delivery-archive",
              "devedition": "net-mozaws-stage-delivery-archive"
            },
            "url_prefix": "https://ftp.stage.mozaws.net"
        },
        "dummy": {}
    }
}
