{
  "provisionerId": "scriptworker-k8s",
  "workerType": "xpi-3-github",
  "taskQueueId": "scriptworker-k8s/xpi-3-github",
  "schedulerId": "xpi-level-3",
  "projectId": "none",
  "taskGroupId": "XP1dJHLKT6ONw7wy7eGqPQ",
  "dependencies": [
    "bpEeoIECRSqfjA09GXgUIw",
    "XP1dJHLKT6ONw7wy7eGqPQ"
  ],
  "requires": "all-completed",
  "routes": [
    "checks"
  ],
  "priority": "lowest",
  "retries": 5,
  "created": "2024-05-14T15:14:23.490Z",
  "deadline": "2024-05-15T15:14:23.490Z",
  "expires": "2025-05-14T15:14:23.490Z",
  "scopes": [
    "project:xpi:releng:github:project:mozilla-extensions/privileged-test-xpi",
    "project:xpi:releng:github:action:release"
  ],
  "payload": {
    "gitTag": "4.0-build1",
    "artifactMap": [
      {
        "paths": {
          "public/build/privileged.xpi": {
            "destinations": [
              "privileged.xpi"
            ]
          }
        },
        "taskId": "bpEeoIECRSqfjA09GXgUIw"
      }
    ],
    "gitRevision": "96c2263a5ca9da43e64647d10b7511b1fcf50e7f",
    "githubOwner": "mozilla-extensions",
    "releaseName": "privileged-test-xpi-4.0-build1",
    "isPrerelease": false,
    "githubRepoName": "privileged-test-xpi",
    "upstreamArtifacts": [
      {
        "paths": [
          "public/build/privileged.xpi"
        ],
        "taskId": "bpEeoIECRSqfjA09GXgUIw",
        "taskType": "signing"
      }
    ]
  },
  "metadata": {
    "name": "release-github-release-github",
    "owner": "gabrielbusta@gmail.com",
    "source": "https://github.com/mozilla-extensions/xpi-manifest/blob/15abb43939b565a844f4a24dfce78361da332e12/taskcluster/kinds/release-github",
    "description": "upload release artifacts to github and publish"
  },
  "tags": {
    "os": "scriptworker",
    "kind": "release-github",
    "label": "release-github-release-github",
    "createdForUser": "gabrielbusta@gmail.com",
    "worker-implementation": "scriptworker"
  },
  "extra": {
    "index": {
      "rank": 0
    },
    "parent": "XP1dJHLKT6ONw7wy7eGqPQ"
  }
}
